aldryn_apphooks_config/__init__.py
aldryn_apphooks_config/admin.py
aldryn_apphooks_config/app_base.py
aldryn_apphooks_config/fields.py
aldryn_apphooks_config/mixins.py
aldryn_apphooks_config/models.py
aldryn_apphooks_config/utils.py
aldryn_apphooks_config/widgets.py
aldryn_apphooks_config/locale/de/LC_MESSAGES/django.mo
aldryn_apphooks_config/locale/de/LC_MESSAGES/django.po
aldryn_apphooks_config/locale/en/LC_MESSAGES/django.mo
aldryn_apphooks_config/locale/en/LC_MESSAGES/django.po
aldryn_apphooks_config/managers/__init__.py
aldryn_apphooks_config/managers/base.py
aldryn_apphooks_config/managers/parler.py
aldryn_apphooks_config/static/css/aldryn_apphooks_config.css
aldryn_apphooks_config/static/js/aldryn_apphooks_config/aldryn_apphooks_config.js
aldryn_apphooks_config/templates/aldryn_apphooks_config/base.html
aldryn_apphooks_config/templates/aldryn_apphooks_config/admin/apphook_config_widget.html
aldryn_apphooks_config/templatetags/__init__.py
aldryn_apphooks_config/templatetags/apphooks_config_tags.py
aldryn_apphooks_config/tests/__init__.py
aldryn_apphooks_config/tests/test_config.py
aldryn_apphooks_config/tests/utils/__init__.py
aldryn_apphooks_config/tests/utils/example/__init__.py
aldryn_apphooks_config/tests/utils/example/admin.py
aldryn_apphooks_config/tests/utils/example/cms_appconfig.py
aldryn_apphooks_config/tests/utils/example/cms_apps.py
aldryn_apphooks_config/tests/utils/example/models.py
aldryn_apphooks_config/tests/utils/example/views.py
aldryn_apphooks_config/tests/utils/example/migrations/0001_initial.py
aldryn_apphooks_config/tests/utils/example/migrations/0002_auto_20191012_2339.py
aldryn_apphooks_config/tests/utils/example/migrations/__init__.py
aldryn_apphooks_config/tests/utils/example/templates/app1/article_detail.html
aldryn_apphooks_config/tests/utils/example/templates/app1/article_list.html
aldryn_apphooks_config/tests/utils/example/templates/app2/article_detail.html
aldryn_apphooks_config-0.7.0.dist-info/LICENSE
aldryn_apphooks_config-0.7.0.dist-info/METADATA
aldryn_apphooks_config-0.7.0.dist-info/WHEEL
aldryn_apphooks_config-0.7.0.dist-info/top_level.txt
aldryn_apphooks_config-0.7.0.dist-info/RECORD
