Metadata-Version: 2.1
Name: aldryn-apphooks-config
Version: 0.7.0
Summary: Namespaces based configuration for Apphooks
Home-page: https://github.com/aldryn/aldryn-apphooks-config
Author: Iacopo Spalletti
Author-email: i.spalletti@nephila.it
License: BSD
Project-URL: Documentation, https://aldryn-apphooks-config.readthedocs.io/
Classifier: License :: OSI Approved :: BSD License
Classifier: Development Status :: 5 - Production/Stable
Classifier: Environment :: Web Environment
Classifier: Framework :: Django
Classifier: Framework :: Django :: 3.2
Classifier: Framework :: Django :: 4.1
Classifier: Framework :: Django :: 4.2
Classifier: Intended Audience :: Developers
Classifier: License :: OSI Approved :: BSD License
Classifier: Operating System :: OS Independent
Classifier: Programming Language :: Python
Classifier: Programming Language :: Python :: 3
Classifier: Programming Language :: Python :: 3.9
Classifier: Programming Language :: Python :: 3.10
Classifier: Programming Language :: Python :: 3.11
Classifier: Operating System :: OS Independent
Classifier: Topic :: Internet :: WWW/HTTP :: Dynamic Content
Classifier: Topic :: Software Development
Classifier: Topic :: Software Development :: Libraries
Requires-Python: >=3.7
License-File: LICENSE
Requires-Dist: django-cms (>=3.9)
Requires-Dist: django-appdata (>=0.3.0)
